rtmlib/__init__.py
rtmlib/version.py
rtmlib/tools/__init__.py
rtmlib/tools/base.py
rtmlib/tools/file.py
rtmlib/tools/object_detection/__init__.py
rtmlib/tools/object_detection/post_processings.py
rtmlib/tools/object_detection/rtmdet.py
rtmlib/tools/object_detection/yolox.py
rtmlib/tools/pose_estimation/__init__.py
rtmlib/tools/pose_estimation/post_processings.py
rtmlib/tools/pose_estimation/pre_processings.py
rtmlib/tools/pose_estimation/rtmo.py
rtmlib/tools/pose_estimation/rtmpose.py
rtmlib/tools/solution/__init__.py
rtmlib/tools/solution/body.py
rtmlib/tools/solution/body_with_feet.py
rtmlib/tools/solution/hand.py
rtmlib/tools/solution/pose_tracker.py
rtmlib/tools/solution/wholebody.py
rtmlib/tools/solution/utils/__init__.py
rtmlib/tools/solution/utils/types.py
rtmlib/visualization/__init__.py
rtmlib/visualization/draw.py
rtmlib/visualization/skeleton/__init__.py
rtmlib/visualization/skeleton/coco133.py
rtmlib/visualization/skeleton/coco17.py
rtmlib/visualization/skeleton/halpe26.py
rtmlib/visualization/skeleton/hand21.py
rtmlib/visualization/skeleton/openpose134.py
rtmlib/visualization/skeleton/openpose18.py
rtmlib_flip-1.0.29.dist-info/LICENSE
rtmlib_flip-1.0.29.dist-info/METADATA
rtmlib_flip-1.0.29.dist-info/WHEEL
rtmlib_flip-1.0.29.dist-info/top_level.txt
rtmlib_flip-1.0.29.dist-info/RECORD
