Metadata-Version: 2.1
Name: rtmlib-flip
Version: 1.0.29
Summary: A library for real-time pose estimation.
Home-page: https://github.com/philip-fu/rtmlib
Author: Philip.Fu
Author-email: fuyang.phil@gmail.com
License: Apache License 2.0
Keywords: pose estimation
Requires-Python: >=3.7
License-File: LICENSE
Provides-Extra: all
Provides-Extra: optional
